<?xml version="1.0" encoding="utf-8"?>
<odoo>
	<data>
		<record model="ir.actions.server" id="caisse_cm_create_customer_account_action_server">
			<field name="name">Créer un compte client</field>
			<field name="model_id" ref="model_res_partner"/>
			<field name="binding_model_id" ref="model_res_partner"/>
			<field name="state">code</field>
			<field name="code">
				record.action_create_customer_account()
			</field>
		</record>
		
		<record model="ir.actions.server" id="caisse_cm_create_supplier_account_action_server">
			<field name="name">Créer un compte fournisseur</field>
			<field name="model_id" ref="model_res_partner"/>
			<field name="binding_model_id" ref="model_res_partner"/>
			<field name="state">code</field>
			<field name="code">
				record.action_create_supplier_account()
			</field>
		</record>
	</data>
</odoo>